asyncjsonrpc/__init__.py
asyncjsonrpc/exceptions.py
asyncjsonrpc/method_group.py
asyncjsonrpc/request.py
asyncjsonrpc/response.py
asyncjsonrpc/client/__init__.py
asyncjsonrpc/client/aiohttp_websocket_client.py
asyncjsonrpc/client/base_client.py
asyncjsonrpc/server/__init__.py
asyncjsonrpc/server/aiohttp_websocket_server.py
asyncjsonrpc/server/base_server.py
tests/__init__.py
tests/test_batch_request.py
tests/test_batch_response.py
tests/test_method_group.py
tests/test_request.py
tests/test_response.py
tests/testutils.py
tests/client/__init__.py
tests/client/test_base_client.py
tests/server/__init__.py
tests/server/test_base_server.py
asyncjsonrpc-1.0.0.dist-info/LICENSE
asyncjsonrpc-1.0.0.dist-info/METADATA
asyncjsonrpc-1.0.0.dist-info/WHEEL
asyncjsonrpc-1.0.0.dist-info/top_level.txt
asyncjsonrpc-1.0.0.dist-info/RECORD
