Metadata-Version: 2.1
Name: asyncjsonrpc
Version: 1.0.0
Summary: Protocol-agnostic asynchronous Python JSON-RPC module
Home-page: https://gitlab.com/hunteradasmith/asyncjsonrpc
Author: Hunter Smith
Author-email: hunter@isrv.pw
License: UNKNOWN
Platform: UNKNOWN
Classifier: Programming Language :: Python :: 3
Classifier: License :: OSI Approved :: MIT License
Classifier: Operating System :: OS Independent
Requires-Python: >=3.6
Requires-Dist: aiohttp
